django_progressbarupload-0.1.7.dist-info/DESCRIPTION.rst
django_progressbarupload-0.1.7.dist-info/METADATA
django_progressbarupload-0.1.7.dist-info/RECORD
django_progressbarupload-0.1.7.dist-info/WHEEL
django_progressbarupload-0.1.7.dist-info/metadata.json
django_progressbarupload-0.1.7.dist-info/top_level.txt
progressbarupload/__init__.py
progressbarupload/test_settings.py
progressbarupload/uploadhandler.py
progressbarupload/urls.py
progressbarupload/views.py
progressbarupload/static/js/progress_bar.js
progressbarupload/templates/progressbarupload/change_form.html
progressbarupload/templatetags/__init__.py
progressbarupload/templatetags/progress_bar.py
progressbarupload/tests/__init__.py
progressbarupload/tests/templatetags.py
progressbarupload/tests/tests.py
