Metadata-Version: 1.1
Name: django-progressbarupload
Version: 0.1.7
Summary: Progress bar upload for Django
Home-page: https://github.com/ouhouhsami/django-progressbarupload
Author: ouhouhsami
Author-email: samuel.goldszmidt@gmail.com
License: BSD License
Platform: UNKNOWN
Classifier: Environment :: Web Environment
Classifier: Framework :: Django
Classifier: Intended Audience :: Developers
Classifier: License :: OSI Approved :: BSD License
Classifier: Operating System :: OS Independent
Classifier: Programming Language :: Python
Classifier: Programming Language :: Python :: 2.7
Classifier: Programming Language :: Python :: 3
Classifier: Topic :: Internet :: WWW/HTTP
Classifier: Topic :: Internet :: WWW/HTTP :: Dynamic Content
